[
    {
        "name": "张三",
        "age": "10",
        "address": "北京西城区",
        "date": "20191210",
        "state": true
    },
    {
        "name": "李四",
        "age": "11",
        "address": "北京东城区",
        "date": "20191211",
        "state": true
    },
    {
        "name": "王五",
        "age": "12",
        "address": "北京朝阳区",
        "date": "20191212",
        "state": false
    },
    {
        "name": "苗六",
        "age": "13",
        "address": "北京海淀区",
        "date": "20191213",
        "state": true
    }
]